[
  {
    "date_updated": "2020-01-23T00:00:00.000",
    "state": "SC",
    "start_date": "2020-01-16T00:00:00.000",
    "end_date": "2020-01-22T00:00:00.000",
    "tot_cases": "0.0",
    "new_cases": "0.0",
    "tot_deaths": "0.0",
    "new_deaths": "0.0",
    "new_historic_cases": "0",
    "new_historic_deaths": "0"
  },
  {
    "date_updated": "2020-01-30T00:00:00.000",
    "state": "SC",
    "start_date": "2020-01-23T00:00:00.000",
    "end_date": "2020-01-29T00:00:00.000",
    "tot_cases": "0.0",
    "new_cases": "0.0",
    "tot_deaths": "0.0",
    "new_deaths": "0.0",
    "new_historic_cases": "0",
    "new_historic_deaths": "0"
  },
  {
    "date_updated": "2020-02-06T00:00:00.000",
    "state": "SC",
    "start_date": "2020-01-30T00:00:00.000",
    "end_date": "2020-02-05T00:00:00.000",
    "tot_cases": "0.0",
    "new_cases": "0.0",
    "tot_deaths": "0.0",
    "new_deaths": "0.0",
    "new_historic_cases": "0",
    "new_historic_deaths": "0"
  },
  {
    "date_updated": "2020-02-13T00:00:00.000",
    "state": "SC",
    "start_date": "2020-02-06T00:00:00.000",
    "end_date": "2020-02-12T00:00:00.000",
    "tot_cases": "0.0",
    "new_cases": "0.0",
    "tot_deaths": "0.0",
    "new_deaths": "0.0",
    "new_historic_cases": "0",
    "new_historic_deaths": "0"
  },
  {
    "date_updated": "2020-02-20T00:00:00.000",
    "state": "SC",
    "start_date": "2020-02-13T00:00:00.000",
    "end_date": "2020-02-19T00:00:00.000",
    "tot_cases": "0.0",
    "new_cases": "0.0",
    "tot_deaths": "0.0",
    "new_deaths": "0.0",
    "new_historic_cases": "0",
    "new_historic_deaths": "0"
  },
  {
    "date_updated": "2020-02-27T00:00:00.000",
    "state": "SC",
    "start_date": "2020-02-20T00:00:00.000",
    "end_date": "2020-02-26T00:00:00.000",
    "tot_cases": "0.0",
    "new_cases": "0.0",
    "tot_deaths": "0.0",
    "new_deaths": "0.0",
    "new_historic_cases": "0",
    "new_historic_deaths": "0"
  },
  {
    "date_updated": "2020-03-05T00:00:00.000",
    "state": "SC",
    "start_date": "2020-02-27T00:00:00.000",
    "end_date": "2020-03-04T00:00:00.000",
    "tot_cases": "0.0",
    "new_cases": "0.0",
    "tot_deaths": "0.0",
    "new_deaths": "0.0",
    "new_historic_cases": "0",
    "new_historic_deaths": "0"
  },
  {
    "date_updated": "2020-03-12T00:00:00.000",
    "state": "SC",
    "start_date": "2020-03-05T00:00:00.000",
    "end_date": "2020-03-11T00:00:00.000",
    "tot_cases": "10.0",
    "new_cases": "10.0",
    "tot_deaths": "0.0",
    "new_deaths": "0.0",
    "new_historic_cases": "0",
    "new_historic_deaths": "0"
  },
  {
    "date_updated": "2020-03-19T00:00:00.000",
    "state": "SC",
    "start_date": "2020-03-12T00:00:00.000",
    "end_date": "2020-03-18T00:00:00.000",
    "tot_cases": "60.0",
    "new_cases": "50.0",
    "tot_deaths": "1.0",
    "new_deaths": "1.0",
    "new_historic_cases": "0",
    "new_historic_deaths": "0"
  },
  {
    "date_updated": "2020-03-26T00:00:00.000",
    "state": "SC",
    "start_date": "2020-03-19T00:00:00.000",
    "end_date": "2020-03-25T00:00:00.000",
    "tot_cases": "426.0",
    "new_cases": "366.0",
    "tot_deaths": "7.0",
    "new_deaths": "6.0",
    "new_historic_cases": "0",
    "new_historic_deaths": "0"
  },
  {
    "date_updated": "2020-04-02T00:00:00.000",
    "state": "SC",
    "start_date": "2020-03-26T00:00:00.000",
    "end_date": "2020-04-01T00:00:00.000",
    "tot_cases": "1293.0",
    "new_cases": "867.0",
    "tot_deaths": "26.0",
    "new_deaths": "19.0",
    "new_historic_cases": "0",
    "new_historic_deaths": "0"
  },
  {
    "date_updated": "2020-04-09T00:00:00.000",
    "state": "SC",
    "start_date": "2020-04-02T00:00:00.000",
    "end_date": "2020-04-08T00:00:00.000",
    "tot_cases": "2419.0",
    "new_cases": "1126.0",
    "tot_deaths": "51.0",
    "new_deaths": "25.0",
    "new_historic_cases": "0",
    "new_historic_deaths": "0"
  },
  {
    "date_updated": "2020-04-16T00:00:00.000",
    "state": "SC",
    "start_date": "2020-04-09T00:00:00.000",
    "end_date": "2020-04-15T00:00:00.000",
    "tot_cases": "3658.0",
    "new_cases": "1239.0",
    "tot_deaths": "105.0",
    "new_deaths": "54.0",
    "new_historic_cases": "0",
    "new_historic_deaths": "0"
  },
  {
    "date_updated": "2020-04-23T00:00:00.000",
    "state": "SC",
    "start_date": "2020-04-16T00:00:00.000",
    "end_date": "2020-04-22T00:00:00.000",
    "tot_cases": "4761.0",
    "new_cases": "1103.0",
    "tot_deaths": "140.0",
    "new_deaths": "35.0",
    "new_historic_cases": "0",
    "new_historic_deaths": "0"
  },
  {
    "date_updated": "2020-04-30T00:00:00.000",
    "state": "SC",
    "start_date": "2020-04-23T00:00:00.000",
    "end_date": "2020-04-29T00:00:00.000",
    "tot_cases": "5883.0",
    "new_cases": "1122.0",
    "tot_deaths": "231.0",
    "new_deaths": "91.0",
    "new_historic_cases": "0",
    "new_historic_deaths": "0"
  },
  {
    "date_updated": "2020-05-07T00:00:00.000",
    "state": "SC",
    "start_date": "2020-04-30T00:00:00.000",
    "end_date": "2020-05-06T00:00:00.000",
    "tot_cases": "6939.0",
    "new_cases": "1056.0",
    "tot_deaths": "304.0",
    "new_deaths": "73.0",
    "new_historic_cases": "0",
    "new_historic_deaths": "0"
  },
  {
    "date_updated": "2020-05-14T00:00:00.000",
    "state": "SC",
    "start_date": "2020-05-07T00:00:00.000",
    "end_date": "2020-05-13T00:00:00.000",
    "tot_cases": "8038.0",
    "new_cases": "1099.0",
    "tot_deaths": "361.0",
    "new_deaths": "57.0",
    "new_historic_cases": "0",
    "new_historic_deaths": "0"
  },
  {
    "date_updated": "2020-05-21T00:00:00.000",
    "state": "SC",
    "start_date": "2020-05-14T00:00:00.000",
    "end_date": "2020-05-20T00:00:00.000",
    "tot_cases": "9177.0",
    "new_cases": "1139.0",
    "tot_deaths": "407.0",
    "new_deaths": "46.0",
    "new_historic_cases": "0",
    "new_historic_deaths": "0"
  },
  {
    "date_updated": "2020-05-28T00:00:00.000",
    "state": "SC",
    "start_date": "2020-05-21T00:00:00.000",
    "end_date": "2020-05-27T00:00:00.000",
    "tot_cases": "10624.0",
    "new_cases": "1447.0",
    "tot_deaths": "466.0",
    "new_deaths": "59.0",
    "new_historic_cases": "0",
    "new_historic_deaths": "0"
  },
  {
    "date_updated": "2020-06-04T00:00:00.000",
    "state": "SC",
    "start_date": "2020-05-28T00:00:00.000",
    "end_date": "2020-06-03T00:00:00.000",
    "tot_cases": "12470.0",
    "new_cases": "1846.0",
    "tot_deaths": "518.0",
    "new_deaths": "52.0",
    "new_historic_cases": "0",
    "new_historic_deaths": "0"
  },
  {
    "date_updated": "2020-06-11T00:00:00.000",
    "state": "SC",
    "start_date": "2020-06-04T00:00:00.000",
    "end_date": "2020-06-10T00:00:00.000",
    "tot_cases": "15768.0",
    "new_cases": "3298.0",
    "tot_deaths": "575.0",
    "new_deaths": "57.0",
    "new_historic_cases": "0",
    "new_historic_deaths": "0"
  },
  {
    "date_updated": "2020-06-18T00:00:00.000",
    "state": "SC",
    "start_date": "2020-06-11T00:00:00.000",
    "end_date": "2020-06-17T00:00:00.000",
    "tot_cases": "20556.0",
    "new_cases": "4788.0",
    "tot_deaths": "618.0",
    "new_deaths": "43.0",
    "new_historic_cases": "0",
    "new_historic_deaths": "0"
  },
  {
    "date_updated": "2020-06-25T00:00:00.000",
    "state": "SC",
    "start_date": "2020-06-18T00:00:00.000",
    "end_date": "2020-06-24T00:00:00.000",
    "tot_cases": "27898.0",
    "new_cases": "7342.0",
    "tot_deaths": "684.0",
    "new_deaths": "66.0",
    "new_historic_cases": "0",
    "new_historic_deaths": "0"
  },
  {
    "date_updated": "2020-07-02T00:00:00.000",
    "state": "SC",
    "start_date": "2020-06-25T00:00:00.000",
    "end_date": "2020-07-01T00:00:00.000",
    "tot_cases": "37919.0",
    "new_cases": "10021.0",
    "tot_deaths": "765.0",
    "new_deaths": "81.0",
    "new_historic_cases": "0",
    "new_historic_deaths": "0"
  },
  {
    "date_updated": "2020-07-09T00:00:00.000",
    "state": "SC",
    "start_date": "2020-07-02T00:00:00.000",
    "end_date": "2020-07-08T00:00:00.000",
    "tot_cases": "48909.0",
    "new_cases": "10990.0",
    "tot_deaths": "882.0",
    "new_deaths": "117.0",
    "new_historic_cases": "0",
    "new_historic_deaths": "0"
  },
  {
    "date_updated": "2020-07-16T00:00:00.000",
    "state": "SC",
    "start_date": "2020-07-09T00:00:00.000",
    "end_date": "2020-07-15T00:00:00.000",
    "tot_cases": "62245.0",
    "new_cases": "13336.0",
    "tot_deaths": "999.0",
    "new_deaths": "117.0",
    "new_historic_cases": "0",
    "new_historic_deaths": "0"
  },
  {
    "date_updated": "2020-07-23T00:00:00.000",
    "state": "SC",
    "start_date": "2020-07-16T00:00:00.000",
    "end_date": "2020-07-22T00:00:00.000",
    "tot_cases": "75042.0",
    "new_cases": "12797.0",
    "tot_deaths": "1285.0",
    "new_deaths": "286.0",
    "new_historic_cases": "0",
    "new_historic_deaths": "0"
  },
  {
    "date_updated": "2020-07-30T00:00:00.000",
    "state": "SC",
    "start_date": "2020-07-23T00:00:00.000",
    "end_date": "2020-07-29T00:00:00.000",
    "tot_cases": "85847.0",
    "new_cases": "10805.0",
    "tot_deaths": "1615.0",
    "new_deaths": "330.0",
    "new_historic_cases": "0",
    "new_historic_deaths": "0"
  },
  {
    "date_updated": "2020-08-06T00:00:00.000",
    "state": "SC",
    "start_date": "2020-07-30T00:00:00.000",
    "end_date": "2020-08-05T00:00:00.000",
    "tot_cases": "95472.0",
    "new_cases": "9625.0",
    "tot_deaths": "1894.0",
    "new_deaths": "279.0",
    "new_historic_cases": "0",
    "new_historic_deaths": "0"
  },
  {
    "date_updated": "2020-08-13T00:00:00.000",
    "state": "SC",
    "start_date": "2020-08-06T00:00:00.000",
    "end_date": "2020-08-12T00:00:00.000",
    "tot_cases": "102979.0",
    "new_cases": "7507.0",
    "tot_deaths": "2143.0",
    "new_deaths": "249.0",
    "new_historic_cases": "0",
    "new_historic_deaths": "0"
  },
  {
    "date_updated": "2020-08-20T00:00:00.000",
    "state": "SC",
    "start_date": "2020-08-13T00:00:00.000",
    "end_date": "2020-08-19T00:00:00.000",
    "tot_cases": "108413.0",
    "new_cases": "5434.0",
    "tot_deaths": "2358.0",
    "new_deaths": "215.0",
    "new_historic_cases": "0",
    "new_historic_deaths": "0"
  },
  {
    "date_updated": "2020-08-27T00:00:00.000",
    "state": "SC",
    "start_date": "2020-08-20T00:00:00.000",
    "end_date": "2020-08-26T00:00:00.000",
    "tot_cases": "114094.0",
    "new_cases": "5681.0",
    "tot_deaths": "2575.0",
    "new_deaths": "217.0",
    "new_historic_cases": "0",
    "new_historic_deaths": "0"
  },
  {
    "date_updated": "2020-09-03T00:00:00.000",
    "state": "SC",
    "start_date": "2020-08-27T00:00:00.000",
    "end_date": "2020-09-02T00:00:00.000",
    "tot_cases": "120507.0",
    "new_cases": "6413.0",
    "tot_deaths": "2794.0",
    "new_deaths": "219.0",
    "new_historic_cases": "0",
    "new_historic_deaths": "0"
  },
  {
    "date_updated": "2020-09-10T00:00:00.000",
    "state": "SC",
    "start_date": "2020-09-03T00:00:00.000",
    "end_date": "2020-09-09T00:00:00.000",
    "tot_cases": "126213.0",
    "new_cases": "5706.0",
    "tot_deaths": "2941.0",
    "new_deaths": "147.0",
    "new_historic_cases": "0",
    "new_historic_deaths": "0"
  },
  {
    "date_updated": "2020-09-17T00:00:00.000",
    "state": "SC",
    "start_date": "2020-09-10T00:00:00.000",
    "end_date": "2020-09-16T00:00:00.000",
    "tot_cases": "134122.0",
    "new_cases": "7909.0",
    "tot_deaths": "3130.0",
    "new_deaths": "189.0",
    "new_historic_cases": "0",
    "new_historic_deaths": "0"
  },
  {
    "date_updated": "2020-09-24T00:00:00.000",
    "state": "SC",
    "start_date": "2020-09-17T00:00:00.000",
    "end_date": "2020-09-23T00:00:00.000",
    "tot_cases": "141688.0",
    "new_cases": "7566.0",
    "tot_deaths": "3262.0",
    "new_deaths": "132.0",
    "new_historic_cases": "0",
    "new_historic_deaths": "0"
  },
  {
    "date_updated": "2020-10-01T00:00:00.000",
    "state": "SC",
    "start_date": "2020-09-24T00:00:00.000",
    "end_date": "2020-09-30T00:00:00.000",
    "tot_cases": "147957.0",
    "new_cases": "6269.0",
    "tot_deaths": "3376.0",
    "new_deaths": "114.0",
    "new_historic_cases": "0",
    "new_historic_deaths": "0"
  },
  {
    "date_updated": "2020-10-08T00:00:00.000",
    "state": "SC",
    "start_date": "2020-10-01T00:00:00.000",
    "end_date": "2020-10-07T00:00:00.000",
    "tot_cases": "153706.0",
    "new_cases": "5749.0",
    "tot_deaths": "3501.0",
    "new_deaths": "125.0",
    "new_historic_cases": "0",
    "new_historic_deaths": "0"
  },
  {
    "date_updated": "2020-10-15T00:00:00.000",
    "state": "SC",
    "start_date": "2020-10-08T00:00:00.000",
    "end_date": "2020-10-14T00:00:00.000",
    "tot_cases": "159808.0",
    "new_cases": "6102.0",
    "tot_deaths": "3592.0",
    "new_deaths": "91.0",
    "new_historic_cases": "0",
    "new_historic_deaths": "0"
  },
  {
    "date_updated": "2020-10-22T00:00:00.000",
    "state": "SC",
    "start_date": "2020-10-15T00:00:00.000",
    "end_date": "2020-10-21T00:00:00.000",
    "tot_cases": "166360.0",
    "new_cases": "6552.0",
    "tot_deaths": "3707.0",
    "new_deaths": "115.0",
    "new_historic_cases": "0",
    "new_historic_deaths": "0"
  },
  {
    "date_updated": "2020-10-29T00:00:00.000",
    "state": "SC",
    "start_date": "2020-10-22T00:00:00.000",
    "end_date": "2020-10-28T00:00:00.000",
    "tot_cases": "173481.0",
    "new_cases": "7121.0",
    "tot_deaths": "3874.0",
    "new_deaths": "167.0",
    "new_historic_cases": "0",
    "new_historic_deaths": "0"
  },
  {
    "date_updated": "2020-11-05T00:00:00.000",
    "state": "SC",
    "start_date": "2020-10-29T00:00:00.000",
    "end_date": "2020-11-04T00:00:00.000",
    "tot_cases": "180869.0",
    "new_cases": "7388.0",
    "tot_deaths": "3984.0",
    "new_deaths": "110.0",
    "new_historic_cases": "0",
    "new_historic_deaths": "0"
  },
  {
    "date_updated": "2020-11-12T00:00:00.000",
    "state": "SC",
    "start_date": "2020-11-05T00:00:00.000",
    "end_date": "2020-11-11T00:00:00.000",
    "tot_cases": "188996.0",
    "new_cases": "8127.0",
    "tot_deaths": "4076.0",
    "new_deaths": "92.0",
    "new_historic_cases": "0",
    "new_historic_deaths": "0"
  },
  {
    "date_updated": "2020-11-19T00:00:00.000",
    "state": "SC",
    "start_date": "2020-11-12T00:00:00.000",
    "end_date": "2020-11-18T00:00:00.000",
    "tot_cases": "199446.0",
    "new_cases": "10450.0",
    "tot_deaths": "4181.0",
    "new_deaths": "105.0",
    "new_historic_cases": "0",
    "new_historic_deaths": "0"
  },
  {
    "date_updated": "2020-11-26T00:00:00.000",
    "state": "SC",
    "start_date": "2020-11-19T00:00:00.000",
    "end_date": "2020-11-25T00:00:00.000",
    "tot_cases": "210905.0",
    "new_cases": "11459.0",
    "tot_deaths": "4317.0",
    "new_deaths": "136.0",
    "new_historic_cases": "0",
    "new_historic_deaths": "0"
  },
  {
    "date_updated": "2020-12-03T00:00:00.000",
    "state": "SC",
    "start_date": "2020-11-26T00:00:00.000",
    "end_date": "2020-12-02T00:00:00.000",
    "tot_cases": "220835.0",
    "new_cases": "9930.0",
    "tot_deaths": "4445.0",
    "new_deaths": "128.0",
    "new_historic_cases": "0",
    "new_historic_deaths": "0"
  },
  {
    "date_updated": "2020-12-10T00:00:00.000",
    "state": "SC",
    "start_date": "2020-12-03T00:00:00.000",
    "end_date": "2020-12-09T00:00:00.000",
    "tot_cases": "239444.0",
    "new_cases": "18609.0",
    "tot_deaths": "4612.0",
    "new_deaths": "167.0",
    "new_historic_cases": "0",
    "new_historic_deaths": "0"
  },
  {
    "date_updated": "2020-12-17T00:00:00.000",
    "state": "SC",
    "start_date": "2020-12-10T00:00:00.000",
    "end_date": "2020-12-16T00:00:00.000",
    "tot_cases": "260120.0",
    "new_cases": "20676.0",
    "tot_deaths": "4800.0",
    "new_deaths": "188.0",
    "new_historic_cases": "0",
    "new_historic_deaths": "0"
  },
  {
    "date_updated": "2020-12-24T00:00:00.000",
    "state": "SC",
    "start_date": "2020-12-17T00:00:00.000",
    "end_date": "2020-12-23T00:00:00.000",
    "tot_cases": "282230.0",
    "new_cases": "22110.0",
    "tot_deaths": "5028.0",
    "new_deaths": "228.0",
    "new_historic_cases": "0",
    "new_historic_deaths": "0"
  },
  {
    "date_updated": "2020-12-31T00:00:00.000",
    "state": "SC",
    "start_date": "2020-12-24T00:00:00.000",
    "end_date": "2020-12-30T00:00:00.000",
    "tot_cases": "303475.0",
    "new_cases": "21245.0",
    "tot_deaths": "5249.0",
    "new_deaths": "221.0",
    "new_historic_cases": "0",
    "new_historic_deaths": "0"
  },
  {
    "date_updated": "2021-01-07T00:00:00.000",
    "state": "SC",
    "start_date": "2020-12-31T00:00:00.000",
    "end_date": "2021-01-06T00:00:00.000",
    "tot_cases": "333235.0",
    "new_cases": "29760.0",
    "tot_deaths": "5583.0",
    "new_deaths": "334.0",
    "new_historic_cases": "0",
    "new_historic_deaths": "0"
  },
  {
    "date_updated": "2021-01-14T00:00:00.000",
    "state": "SC",
    "start_date": "2021-01-07T00:00:00.000",
    "end_date": "2021-01-13T00:00:00.000",
    "tot_cases": "365378.0",
    "new_cases": "32143.0",
    "tot_deaths": "5911.0",
    "new_deaths": "328.0",
    "new_historic_cases": "0",
    "new_historic_deaths": "0"
  },
  {
    "date_updated": "2021-01-21T00:00:00.000",
    "state": "SC",
    "start_date": "2021-01-14T00:00:00.000",
    "end_date": "2021-01-20T00:00:00.000",
    "tot_cases": "399843.0",
    "new_cases": "34465.0",
    "tot_deaths": "6327.0",
    "new_deaths": "416.0",
    "new_historic_cases": "0",
    "new_historic_deaths": "0"
  },
  {
    "date_updated": "2021-01-28T00:00:00.000",
    "state": "SC",
    "start_date": "2021-01-21T00:00:00.000",
    "end_date": "2021-01-27T00:00:00.000",
    "tot_cases": "427231.0",
    "new_cases": "27388.0",
    "tot_deaths": "6669.0",
    "new_deaths": "342.0",
    "new_historic_cases": "0",
    "new_historic_deaths": "0"
  },
  {
    "date_updated": "2021-02-04T00:00:00.000",
    "state": "SC",
    "start_date": "2021-01-28T00:00:00.000",
    "end_date": "2021-02-03T00:00:00.000",
    "tot_cases": "450794.0",
    "new_cases": "23563.0",
    "tot_deaths": "7395.0",
    "new_deaths": "726.0",
    "new_historic_cases": "0",
    "new_historic_deaths": "0"
  },
  {
    "date_updated": "2021-02-11T00:00:00.000",
    "state": "SC",
    "start_date": "2021-02-04T00:00:00.000",
    "end_date": "2021-02-10T00:00:00.000",
    "tot_cases": "473140.0",
    "new_cases": "22346.0",
    "tot_deaths": "7742.0",
    "new_deaths": "347.0",
    "new_historic_cases": "0",
    "new_historic_deaths": "0"
  },
  {
    "date_updated": "2021-02-18T00:00:00.000",
    "state": "SC",
    "start_date": "2021-02-11T00:00:00.000",
    "end_date": "2021-02-17T00:00:00.000",
    "tot_cases": "492369.0",
    "new_cases": "19229.0",
    "tot_deaths": "8116.0",
    "new_deaths": "374.0",
    "new_historic_cases": "0",
    "new_historic_deaths": "0"
  },
  {
    "date_updated": "2021-02-25T00:00:00.000",
    "state": "SC",
    "start_date": "2021-02-18T00:00:00.000",
    "end_date": "2021-02-24T00:00:00.000",
    "tot_cases": "509044.0",
    "new_cases": "16675.0",
    "tot_deaths": "8399.0",
    "new_deaths": "283.0",
    "new_historic_cases": "0",
    "new_historic_deaths": "0"
  },
  {
    "date_updated": "2021-03-04T00:00:00.000",
    "state": "SC",
    "start_date": "2021-02-25T00:00:00.000",
    "end_date": "2021-03-03T00:00:00.000",
    "tot_cases": "519996.0",
    "new_cases": "10952.0",
    "tot_deaths": "8619.0",
    "new_deaths": "220.0",
    "new_historic_cases": "0",
    "new_historic_deaths": "0"
  },
  {
    "date_updated": "2021-03-11T00:00:00.000",
    "state": "SC",
    "start_date": "2021-03-04T00:00:00.000",
    "end_date": "2021-03-10T00:00:00.000",
    "tot_cases": "528473.0",
    "new_cases": "8477.0",
    "tot_deaths": "8782.0",
    "new_deaths": "163.0",
    "new_historic_cases": "0",
    "new_historic_deaths": "0"
  },
  {
    "date_updated": "2021-03-18T00:00:00.000",
    "state": "SC",
    "start_date": "2021-03-11T00:00:00.000",
    "end_date": "2021-03-17T00:00:00.000",
    "tot_cases": "536100.0",
    "new_cases": "7627.0",
    "tot_deaths": "8929.0",
    "new_deaths": "147.0",
    "new_historic_cases": "0",
    "new_historic_deaths": "0"
  },
  {
    "date_updated": "2021-03-25T00:00:00.000",
    "state": "SC",
    "start_date": "2021-03-18T00:00:00.000",
    "end_date": "2021-03-24T00:00:00.000",
    "tot_cases": "543932.0",
    "new_cases": "7832.0",
    "tot_deaths": "9055.0",
    "new_deaths": "126.0",
    "new_historic_cases": "0",
    "new_historic_deaths": "0"
  },
  {
    "date_updated": "2021-04-01T00:00:00.000",
    "state": "SC",
    "start_date": "2021-03-25T00:00:00.000",
    "end_date": "2021-03-31T00:00:00.000",
    "tot_cases": "551631.0",
    "new_cases": "7699.0",
    "tot_deaths": "9145.0",
    "new_deaths": "90.0",
    "new_historic_cases": "0",
    "new_historic_deaths": "0"
  },
  {
    "date_updated": "2021-04-08T00:00:00.000",
    "state": "SC",
    "start_date": "2021-04-01T00:00:00.000",
    "end_date": "2021-04-07T00:00:00.000",
    "tot_cases": "558631.0",
    "new_cases": "7000.0",
    "tot_deaths": "9210.0",
    "new_deaths": "65.0",
    "new_historic_cases": "0",
    "new_historic_deaths": "0"
  },
  {
    "date_updated": "2021-04-15T00:00:00.000",
    "state": "SC",
    "start_date": "2021-04-08T00:00:00.000",
    "end_date": "2021-04-14T00:00:00.000",
    "tot_cases": "564933.0",
    "new_cases": "6302.0",
    "tot_deaths": "9299.0",
    "new_deaths": "89.0",
    "new_historic_cases": "0",
    "new_historic_deaths": "0"
  },
  {
    "date_updated": "2021-04-22T00:00:00.000",
    "state": "SC",
    "start_date": "2021-04-15T00:00:00.000",
    "end_date": "2021-04-21T00:00:00.000",
    "tot_cases": "571369.0",
    "new_cases": "6436.0",
    "tot_deaths": "9362.0",
    "new_deaths": "63.0",
    "new_historic_cases": "0",
    "new_historic_deaths": "0"
  },
  {
    "date_updated": "2021-04-29T00:00:00.000",
    "state": "SC",
    "start_date": "2021-04-22T00:00:00.000",
    "end_date": "2021-04-28T00:00:00.000",
    "tot_cases": "576640.0",
    "new_cases": "5271.0",
    "tot_deaths": "9469.0",
    "new_deaths": "107.0",
    "new_historic_cases": "0",
    "new_historic_deaths": "0"
  },
  {
    "date_updated": "2021-05-06T00:00:00.000",
    "state": "SC",
    "start_date": "2021-04-29T00:00:00.000",
    "end_date": "2021-05-05T00:00:00.000",
    "tot_cases": "581839.0",
    "new_cases": "5199.0",
    "tot_deaths": "9533.0",
    "new_deaths": "64.0",
    "new_historic_cases": "0",
    "new_historic_deaths": "0"
  },
  {
    "date_updated": "2021-05-13T00:00:00.000",
    "state": "SC",
    "start_date": "2021-05-06T00:00:00.000",
    "end_date": "2021-05-12T00:00:00.000",
    "tot_cases": "585600.0",
    "new_cases": "3761.0",
    "tot_deaths": "9589.0",
    "new_deaths": "56.0",
    "new_historic_cases": "0",
    "new_historic_deaths": "0"
  },
  {
    "date_updated": "2021-05-20T00:00:00.000",
    "state": "SC",
    "start_date": "2021-05-13T00:00:00.000",
    "end_date": "2021-05-19T00:00:00.000",
    "tot_cases": "589471.0",
    "new_cases": "3871.0",
    "tot_deaths": "9647.0",
    "new_deaths": "58.0",
    "new_historic_cases": "0",
    "new_historic_deaths": "0"
  },
  {
    "date_updated": "2021-05-27T00:00:00.000",
    "state": "SC",
    "start_date": "2021-05-20T00:00:00.000",
    "end_date": "2021-05-26T00:00:00.000",
    "tot_cases": "591834.0",
    "new_cases": "2363.0",
    "tot_deaths": "9687.0",
    "new_deaths": "40.0",
    "new_historic_cases": "0",
    "new_historic_deaths": "0"
  },
  {
    "date_updated": "2021-06-03T00:00:00.000",
    "state": "SC",
    "start_date": "2021-05-27T00:00:00.000",
    "end_date": "2021-06-02T00:00:00.000",
    "tot_cases": "593384.0",
    "new_cases": "1550.0",
    "tot_deaths": "9713.0",
    "new_deaths": "26.0",
    "new_historic_cases": "0",
    "new_historic_deaths": "0"
  },
  {
    "date_updated": "2021-06-10T00:00:00.000",
    "state": "SC",
    "start_date": "2021-06-03T00:00:00.000",
    "end_date": "2021-06-09T00:00:00.000",
    "tot_cases": "594444.0",
    "new_cases": "1060.0",
    "tot_deaths": "9747.0",
    "new_deaths": "34.0",
    "new_historic_cases": "0",
    "new_historic_deaths": "0"
  },
  {
    "date_updated": "2021-06-17T00:00:00.000",
    "state": "SC",
    "start_date": "2021-06-10T00:00:00.000",
    "end_date": "2021-06-16T00:00:00.000",
    "tot_cases": "595217.0",
    "new_cases": "773.0",
    "tot_deaths": "9776.0",
    "new_deaths": "29.0",
    "new_historic_cases": "0",
    "new_historic_deaths": "0"
  },
  {
    "date_updated": "2021-06-24T00:00:00.000",
    "state": "SC",
    "start_date": "2021-06-17T00:00:00.000",
    "end_date": "2021-06-23T00:00:00.000",
    "tot_cases": "595843.0",
    "new_cases": "626.0",
    "tot_deaths": "9792.0",
    "new_deaths": "16.0",
    "new_historic_cases": "0",
    "new_historic_deaths": "0"
  },
  {
    "date_updated": "2021-07-01T00:00:00.000",
    "state": "SC",
    "start_date": "2021-06-24T00:00:00.000",
    "end_date": "2021-06-30T00:00:00.000",
    "tot_cases": "596813.0",
    "new_cases": "970.0",
    "tot_deaths": "9810.0",
    "new_deaths": "18.0",
    "new_historic_cases": "0",
    "new_historic_deaths": "0"
  },
  {
    "date_updated": "2021-07-08T00:00:00.000",
    "state": "SC",
    "start_date": "2021-07-01T00:00:00.000",
    "end_date": "2021-07-07T00:00:00.000",
    "tot_cases": "598227.0",
    "new_cases": "1414.0",
    "tot_deaths": "9831.0",
    "new_deaths": "21.0",
    "new_historic_cases": "0",
    "new_historic_deaths": "0"
  },
  {
    "date_updated": "2021-07-15T00:00:00.000",
    "state": "SC",
    "start_date": "2021-07-08T00:00:00.000",
    "end_date": "2021-07-14T00:00:00.000",
    "tot_cases": "600606.0",
    "new_cases": "2379.0",
    "tot_deaths": "9844.0",
    "new_deaths": "13.0",
    "new_historic_cases": "0",
    "new_historic_deaths": "0"
  },
  {
    "date_updated": "2021-07-22T00:00:00.000",
    "state": "SC",
    "start_date": "2021-07-15T00:00:00.000",
    "end_date": "2021-07-21T00:00:00.000",
    "tot_cases": "604653.0",
    "new_cases": "4047.0",
    "tot_deaths": "9869.0",
    "new_deaths": "25.0",
    "new_historic_cases": "0",
    "new_historic_deaths": "0"
  },
  {
    "date_updated": "2021-07-29T00:00:00.000",
    "state": "SC",
    "start_date": "2021-07-22T00:00:00.000",
    "end_date": "2021-07-28T00:00:00.000",
    "tot_cases": "613033.0",
    "new_cases": "8380.0",
    "tot_deaths": "9894.0",
    "new_deaths": "25.0",
    "new_historic_cases": "0",
    "new_historic_deaths": "0"
  },
  {
    "date_updated": "2021-08-05T00:00:00.000",
    "state": "SC",
    "start_date": "2021-07-29T00:00:00.000",
    "end_date": "2021-08-04T00:00:00.000",
    "tot_cases": "628203.0",
    "new_cases": "15170.0",
    "tot_deaths": "9930.0",
    "new_deaths": "36.0",
    "new_historic_cases": "0",
    "new_historic_deaths": "0"
  },
  {
    "date_updated": "2021-08-12T00:00:00.000",
    "state": "SC",
    "start_date": "2021-08-05T00:00:00.000",
    "end_date": "2021-08-11T00:00:00.000",
    "tot_cases": "648508.0",
    "new_cases": "20305.0",
    "tot_deaths": "10007.0",
    "new_deaths": "77.0",
    "new_historic_cases": "0",
    "new_historic_deaths": "0"
  },
  {
    "date_updated": "2021-08-19T00:00:00.000",
    "state": "SC",
    "start_date": "2021-08-12T00:00:00.000",
    "end_date": "2021-08-18T00:00:00.000",
    "tot_cases": "673172.0",
    "new_cases": "24664.0",
    "tot_deaths": "10141.0",
    "new_deaths": "134.0",
    "new_historic_cases": "0",
    "new_historic_deaths": "0"
  },
  {
    "date_updated": "2021-08-26T00:00:00.000",
    "state": "SC",
    "start_date": "2021-08-19T00:00:00.000",
    "end_date": "2021-08-25T00:00:00.000",
    "tot_cases": "702894.0",
    "new_cases": "29722.0",
    "tot_deaths": "10357.0",
    "new_deaths": "216.0",
    "new_historic_cases": "0",
    "new_historic_deaths": "0"
  },
  {
    "date_updated": "2021-09-02T00:00:00.000",
    "state": "SC",
    "start_date": "2021-08-26T00:00:00.000",
    "end_date": "2021-09-01T00:00:00.000",
    "tot_cases": "740634.0",
    "new_cases": "37740.0",
    "tot_deaths": "10684.0",
    "new_deaths": "327.0",
    "new_historic_cases": "0",
    "new_historic_deaths": "0"
  },
  {
    "date_updated": "2021-09-09T00:00:00.000",
    "state": "SC",
    "start_date": "2021-09-02T00:00:00.000",
    "end_date": "2021-09-08T00:00:00.000",
    "tot_cases": "776342.0",
    "new_cases": "35708.0",
    "tot_deaths": "10996.0",
    "new_deaths": "312.0",
    "new_historic_cases": "0",
    "new_historic_deaths": "0"
  },
  {
    "date_updated": "2021-09-16T00:00:00.000",
    "state": "SC",
    "start_date": "2021-09-09T00:00:00.000",
    "end_date": "2021-09-15T00:00:00.000",
    "tot_cases": "809780.0",
    "new_cases": "33438.0",
    "tot_deaths": "11483.0",
    "new_deaths": "487.0",
    "new_historic_cases": "0",
    "new_historic_deaths": "0"
  },
  {
    "date_updated": "2021-09-23T00:00:00.000",
    "state": "SC",
    "start_date": "2021-09-16T00:00:00.000",
    "end_date": "2021-09-22T00:00:00.000",
    "tot_cases": "834880.0",
    "new_cases": "25100.0",
    "tot_deaths": "11914.0",
    "new_deaths": "431.0",
    "new_historic_cases": "0",
    "new_historic_deaths": "0"
  },
  {
    "date_updated": "2021-09-30T00:00:00.000",
    "state": "SC",
    "start_date": "2021-09-23T00:00:00.000",
    "end_date": "2021-09-29T00:00:00.000",
    "tot_cases": "854875.0",
    "new_cases": "19995.0",
    "tot_deaths": "12372.0",
    "new_deaths": "458.0",
    "new_historic_cases": "0",
    "new_historic_deaths": "0"
  },
  {
    "date_updated": "2021-10-07T00:00:00.000",
    "state": "SC",
    "start_date": "2021-09-30T00:00:00.000",
    "end_date": "2021-10-06T00:00:00.000",
    "tot_cases": "869838.0",
    "new_cases": "14963.0",
    "tot_deaths": "12784.0",
    "new_deaths": "412.0",
    "new_historic_cases": "0",
    "new_historic_deaths": "0"
  },
  {
    "date_updated": "2021-10-14T00:00:00.000",
    "state": "SC",
    "start_date": "2021-10-07T00:00:00.000",
    "end_date": "2021-10-13T00:00:00.000",
    "tot_cases": "880984.0",
    "new_cases": "11146.0",
    "tot_deaths": "13094.0",
    "new_deaths": "310.0",
    "new_historic_cases": "0",
    "new_historic_deaths": "0"
  },
  {
    "date_updated": "2021-10-21T00:00:00.000",
    "state": "SC",
    "start_date": "2021-10-14T00:00:00.000",
    "end_date": "2021-10-20T00:00:00.000",
    "tot_cases": "889100.0",
    "new_cases": "8116.0",
    "tot_deaths": "13367.0",
    "new_deaths": "273.0",
    "new_historic_cases": "0",
    "new_historic_deaths": "0"
  },
  {
    "date_updated": "2021-10-28T00:00:00.000",
    "state": "SC",
    "start_date": "2021-10-21T00:00:00.000",
    "end_date": "2021-10-27T00:00:00.000",
    "tot_cases": "894924.0",
    "new_cases": "5824.0",
    "tot_deaths": "13604.0",
    "new_deaths": "237.0",
    "new_historic_cases": "0",
    "new_historic_deaths": "0"
  },
  {
    "date_updated": "2021-11-04T00:00:00.000",
    "state": "SC",
    "start_date": "2021-10-28T00:00:00.000",
    "end_date": "2021-11-03T00:00:00.000",
    "tot_cases": "900468.0",
    "new_cases": "5544.0",
    "tot_deaths": "13800.0",
    "new_deaths": "196.0",
    "new_historic_cases": "0",
    "new_historic_deaths": "0"
  },
  {
    "date_updated": "2021-11-11T00:00:00.000",
    "state": "SC",
    "start_date": "2021-11-04T00:00:00.000",
    "end_date": "2021-11-10T00:00:00.000",
    "tot_cases": "905179.0",
    "new_cases": "4711.0",
    "tot_deaths": "13921.0",
    "new_deaths": "121.0",
    "new_historic_cases": "0",
    "new_historic_deaths": "0"
  },
  {
    "date_updated": "2021-11-18T00:00:00.000",
    "state": "SC",
    "start_date": "2021-11-11T00:00:00.000",
    "end_date": "2021-11-17T00:00:00.000",
    "tot_cases": "909906.0",
    "new_cases": "4727.0",
    "tot_deaths": "14063.0",
    "new_deaths": "142.0",
    "new_historic_cases": "0",
    "new_historic_deaths": "0"
  },
  {
    "date_updated": "2021-11-25T00:00:00.000",
    "state": "SC",
    "start_date": "2021-11-18T00:00:00.000",
    "end_date": "2021-11-24T00:00:00.000",
    "tot_cases": "914966.0",
    "new_cases": "5060.0",
    "tot_deaths": "14153.0",
    "new_deaths": "90.0",
    "new_historic_cases": "0",
    "new_historic_deaths": "0"
  },
  {
    "date_updated": "2021-12-02T00:00:00.000",
    "state": "SC",
    "start_date": "2021-11-25T00:00:00.000",
    "end_date": "2021-12-01T00:00:00.000",
    "tot_cases": "919186.0",
    "new_cases": "4220.0",
    "tot_deaths": "14233.0",
    "new_deaths": "80.0",
    "new_historic_cases": "0",
    "new_historic_deaths": "0"
  },
  {
    "date_updated": "2021-12-09T00:00:00.000",
    "state": "SC",
    "start_date": "2021-12-02T00:00:00.000",
    "end_date": "2021-12-08T00:00:00.000",
    "tot_cases": "926455.0",
    "new_cases": "7269.0",
    "tot_deaths": "14334.0",
    "new_deaths": "101.0",
    "new_historic_cases": "0",
    "new_historic_deaths": "0"
  },
  {
    "date_updated": "2021-12-16T00:00:00.000",
    "state": "SC",
    "start_date": "2021-12-09T00:00:00.000",
    "end_date": "2021-12-15T00:00:00.000",
    "tot_cases": "933754.0",
    "new_cases": "7299.0",
    "tot_deaths": "14430.0",
    "new_deaths": "96.0",
    "new_historic_cases": "0",
    "new_historic_deaths": "0"
  },
  {
    "date_updated": "2021-12-23T00:00:00.000",
    "state": "SC",
    "start_date": "2021-12-16T00:00:00.000",
    "end_date": "2021-12-22T00:00:00.000",
    "tot_cases": "942360.0",
    "new_cases": "8606.0",
    "tot_deaths": "14526.0",
    "new_deaths": "96.0",
    "new_historic_cases": "0",
    "new_historic_deaths": "0"
  },
  {
    "date_updated": "2021-12-30T00:00:00.000",
    "state": "SC",
    "start_date": "2021-12-23T00:00:00.000",
    "end_date": "2021-12-29T00:00:00.000",
    "tot_cases": "960195.0",
    "new_cases": "17835.0",
    "tot_deaths": "14610.0",
    "new_deaths": "84.0",
    "new_historic_cases": "0",
    "new_historic_deaths": "0"
  },
  {
    "date_updated": "2022-01-06T00:00:00.000",
    "state": "SC",
    "start_date": "2021-12-30T00:00:00.000",
    "end_date": "2022-01-05T00:00:00.000",
    "tot_cases": "1018435.0",
    "new_cases": "58240.0",
    "tot_deaths": "14715.0",
    "new_deaths": "105.0",
    "new_historic_cases": "0",
    "new_historic_deaths": "0"
  },
  {
    "date_updated": "2022-01-13T00:00:00.000",
    "state": "SC",
    "start_date": "2022-01-06T00:00:00.000",
    "end_date": "2022-01-12T00:00:00.000",
    "tot_cases": "1114781.0",
    "new_cases": "96346.0",
    "tot_deaths": "14847.0",
    "new_deaths": "132.0",
    "new_historic_cases": "0",
    "new_historic_deaths": "0"
  },
  {
    "date_updated": "2022-01-20T00:00:00.000",
    "state": "SC",
    "start_date": "2022-01-13T00:00:00.000",
    "end_date": "2022-01-19T00:00:00.000",
    "tot_cases": "1236732.0",
    "new_cases": "121951.0",
    "tot_deaths": "15029.0",
    "new_deaths": "182.0",
    "new_historic_cases": "0",
    "new_historic_deaths": "0"
  },
  {
    "date_updated": "2022-01-27T00:00:00.000",
    "state": "SC",
    "start_date": "2022-01-20T00:00:00.000",
    "end_date": "2022-01-26T00:00:00.000",
    "tot_cases": "1328450.0",
    "new_cases": "91718.0",
    "tot_deaths": "15156.0",
    "new_deaths": "127.0",
    "new_historic_cases": "0",
    "new_historic_deaths": "0"
  },
  {
    "date_updated": "2022-02-03T00:00:00.000",
    "state": "SC",
    "start_date": "2022-01-27T00:00:00.000",
    "end_date": "2022-02-02T00:00:00.000",
    "tot_cases": "1394651.0",
    "new_cases": "66201.0",
    "tot_deaths": "15609.0",
    "new_deaths": "453.0",
    "new_historic_cases": "0",
    "new_historic_deaths": "0"
  },
  {
    "date_updated": "2022-02-10T00:00:00.000",
    "state": "SC",
    "start_date": "2022-02-03T00:00:00.000",
    "end_date": "2022-02-09T00:00:00.000",
    "tot_cases": "1427869.0",
    "new_cases": "33218.0",
    "tot_deaths": "16018.0",
    "new_deaths": "409.0",
    "new_historic_cases": "0",
    "new_historic_deaths": "0"
  },
  {
    "date_updated": "2022-02-17T00:00:00.000",
    "state": "SC",
    "start_date": "2022-02-10T00:00:00.000",
    "end_date": "2022-02-16T00:00:00.000",
    "tot_cases": "1445383.0",
    "new_cases": "17514.0",
    "tot_deaths": "16407.0",
    "new_deaths": "389.0",
    "new_historic_cases": "0",
    "new_historic_deaths": "0"
  },
  {
    "date_updated": "2022-02-24T00:00:00.000",
    "state": "SC",
    "start_date": "2022-02-17T00:00:00.000",
    "end_date": "2022-02-23T00:00:00.000",
    "tot_cases": "1456998.0",
    "new_cases": "11615.0",
    "tot_deaths": "16614.0",
    "new_deaths": "207.0",
    "new_historic_cases": "0",
    "new_historic_deaths": "0"
  },
  {
    "date_updated": "2022-03-03T00:00:00.000",
    "state": "SC",
    "start_date": "2022-02-24T00:00:00.000",
    "end_date": "2022-03-02T00:00:00.000",
    "tot_cases": "1461791.0",
    "new_cases": "4793.0",
    "tot_deaths": "16928.0",
    "new_deaths": "314.0",
    "new_historic_cases": "0",
    "new_historic_deaths": "0"
  },
  {
    "date_updated": "2022-03-10T00:00:00.000",
    "state": "SC",
    "start_date": "2022-03-03T00:00:00.000",
    "end_date": "2022-03-09T00:00:00.000",
    "tot_cases": "1464213.0",
    "new_cases": "2422.0",
    "tot_deaths": "17251.0",
    "new_deaths": "323.0",
    "new_historic_cases": "0",
    "new_historic_deaths": "0"
  },
  {
    "date_updated": "2022-03-17T00:00:00.000",
    "state": "SC",
    "start_date": "2022-03-10T00:00:00.000",
    "end_date": "2022-03-16T00:00:00.000",
    "tot_cases": "1465736.0",
    "new_cases": "1523.0",
    "tot_deaths": "17380.0",
    "new_deaths": "129.0",
    "new_historic_cases": "0",
    "new_historic_deaths": "0"
  },
  {
    "date_updated": "2022-03-24T00:00:00.000",
    "state": "SC",
    "start_date": "2022-03-17T00:00:00.000",
    "end_date": "2022-03-23T00:00:00.000",
    "tot_cases": "1467112.0",
    "new_cases": "1376.0",
    "tot_deaths": "17493.0",
    "new_deaths": "113.0",
    "new_historic_cases": "0",
    "new_historic_deaths": "0"
  },
  {
    "date_updated": "2022-03-31T00:00:00.000",
    "state": "SC",
    "start_date": "2022-03-24T00:00:00.000",
    "end_date": "2022-03-30T00:00:00.000",
    "tot_cases": "1468134.0",
    "new_cases": "1022.0",
    "tot_deaths": "17587.0",
    "new_deaths": "94.0",
    "new_historic_cases": "0",
    "new_historic_deaths": "0"
  },
  {
    "date_updated": "2022-04-07T00:00:00.000",
    "state": "SC",
    "start_date": "2022-03-31T00:00:00.000",
    "end_date": "2022-04-06T00:00:00.000",
    "tot_cases": "1469699.0",
    "new_cases": "1565.0",
    "tot_deaths": "17650.0",
    "new_deaths": "63.0",
    "new_historic_cases": "0",
    "new_historic_deaths": "0"
  },
  {
    "date_updated": "2022-04-14T00:00:00.000",
    "state": "SC",
    "start_date": "2022-04-07T00:00:00.000",
    "end_date": "2022-04-13T00:00:00.000",
    "tot_cases": "1470597.0",
    "new_cases": "898.0",
    "tot_deaths": "17698.0",
    "new_deaths": "48.0",
    "new_historic_cases": "0",
    "new_historic_deaths": "0"
  },
  {
    "date_updated": "2022-04-21T00:00:00.000",
    "state": "SC",
    "start_date": "2022-04-14T00:00:00.000",
    "end_date": "2022-04-20T00:00:00.000",
    "tot_cases": "1472093.0",
    "new_cases": "1496.0",
    "tot_deaths": "17734.0",
    "new_deaths": "36.0",
    "new_historic_cases": "0",
    "new_historic_deaths": "0"
  },
  {
    "date_updated": "2022-04-28T00:00:00.000",
    "state": "SC",
    "start_date": "2022-04-21T00:00:00.000",
    "end_date": "2022-04-27T00:00:00.000",
    "tot_cases": "1474274.0",
    "new_cases": "2181.0",
    "tot_deaths": "17767.0",
    "new_deaths": "33.0",
    "new_historic_cases": "0",
    "new_historic_deaths": "0"
  },
  {
    "date_updated": "2022-05-05T00:00:00.000",
    "state": "SC",
    "start_date": "2022-04-28T00:00:00.000",
    "end_date": "2022-05-04T00:00:00.000",
    "tot_cases": "1477460.0",
    "new_cases": "3186.0",
    "tot_deaths": "17848.0",
    "new_deaths": "81.0",
    "new_historic_cases": "0",
    "new_historic_deaths": "0"
  },
  {
    "date_updated": "2022-05-12T00:00:00.000",
    "state": "SC",
    "start_date": "2022-05-05T00:00:00.000",
    "end_date": "2022-05-11T00:00:00.000",
    "tot_cases": "1481975.0",
    "new_cases": "4515.0",
    "tot_deaths": "17868.0",
    "new_deaths": "20.0",
    "new_historic_cases": "0",
    "new_historic_deaths": "0"
  },
  {
    "date_updated": "2022-05-19T00:00:00.000",
    "state": "SC",
    "start_date": "2022-05-12T00:00:00.000",
    "end_date": "2022-05-18T00:00:00.000",
    "tot_cases": "1487728.0",
    "new_cases": "5753.0",
    "tot_deaths": "17890.0",
    "new_deaths": "22.0",
    "new_historic_cases": "0",
    "new_historic_deaths": "0"
  },
  {
    "date_updated": "2022-05-26T00:00:00.000",
    "state": "SC",
    "start_date": "2022-05-19T00:00:00.000",
    "end_date": "2022-05-25T00:00:00.000",
    "tot_cases": "1495762.0",
    "new_cases": "8034.0",
    "tot_deaths": "17905.0",
    "new_deaths": "15.0",
    "new_historic_cases": "0",
    "new_historic_deaths": "0"
  },
  {
    "date_updated": "2022-06-02T00:00:00.000",
    "state": "SC",
    "start_date": "2022-05-26T00:00:00.000",
    "end_date": "2022-06-01T00:00:00.000",
    "tot_cases": "1504967.0",
    "new_cases": "9205.0",
    "tot_deaths": "17907.0",
    "new_deaths": "2.0",
    "new_historic_cases": "0",
    "new_historic_deaths": "0"
  },
  {
    "date_updated": "2022-06-09T00:00:00.000",
    "state": "SC",
    "start_date": "2022-06-02T00:00:00.000",
    "end_date": "2022-06-08T00:00:00.000",
    "tot_cases": "1514423.0",
    "new_cases": "9456.0",
    "tot_deaths": "17970.0",
    "new_deaths": "63.0",
    "new_historic_cases": "0",
    "new_historic_deaths": "0"
  },
  {
    "date_updated": "2022-06-16T00:00:00.000",
    "state": "SC",
    "start_date": "2022-06-09T00:00:00.000",
    "end_date": "2022-06-15T00:00:00.000",
    "tot_cases": "1524771.0",
    "new_cases": "10348.0",
    "tot_deaths": "17995.0",
    "new_deaths": "25.0",
    "new_historic_cases": "0",
    "new_historic_deaths": "0"
  },
  {
    "date_updated": "2022-06-23T00:00:00.000",
    "state": "SC",
    "start_date": "2022-06-16T00:00:00.000",
    "end_date": "2022-06-22T00:00:00.000",
    "tot_cases": "1535392.0",
    "new_cases": "10621.0",
    "tot_deaths": "18007.0",
    "new_deaths": "12.0",
    "new_historic_cases": "0",
    "new_historic_deaths": "0"
  },
  {
    "date_updated": "2022-06-30T00:00:00.000",
    "state": "SC",
    "start_date": "2022-06-23T00:00:00.000",
    "end_date": "2022-06-29T00:00:00.000",
    "tot_cases": "1546406.0",
    "new_cases": "11014.0",
    "tot_deaths": "18033.0",
    "new_deaths": "26.0",
    "new_historic_cases": "0",
    "new_historic_deaths": "0"
  },
  {
    "date_updated": "2022-07-07T00:00:00.000",
    "state": "SC",
    "start_date": "2022-06-30T00:00:00.000",
    "end_date": "2022-07-06T00:00:00.000",
    "tot_cases": "1560139.0",
    "new_cases": "13733.0",
    "tot_deaths": "18043.0",
    "new_deaths": "10.0",
    "new_historic_cases": "0",
    "new_historic_deaths": "0"
  },
  {
    "date_updated": "2022-07-14T00:00:00.000",
    "state": "SC",
    "start_date": "2022-07-07T00:00:00.000",
    "end_date": "2022-07-13T00:00:00.000",
    "tot_cases": "1573585.0",
    "new_cases": "13446.0",
    "tot_deaths": "18055.0",
    "new_deaths": "12.0",
    "new_historic_cases": "0",
    "new_historic_deaths": "0"
  },
  {
    "date_updated": "2022-07-21T00:00:00.000",
    "state": "SC",
    "start_date": "2022-07-14T00:00:00.000",
    "end_date": "2022-07-20T00:00:00.000",
    "tot_cases": "1587503.0",
    "new_cases": "13918.0",
    "tot_deaths": "18131.0",
    "new_deaths": "76.0",
    "new_historic_cases": "0",
    "new_historic_deaths": "0"
  },
  {
    "date_updated": "2022-07-28T00:00:00.000",
    "state": "SC",
    "start_date": "2022-07-21T00:00:00.000",
    "end_date": "2022-07-27T00:00:00.000",
    "tot_cases": "1605165.0",
    "new_cases": "17662.0",
    "tot_deaths": "18189.0",
    "new_deaths": "58.0",
    "new_historic_cases": "0",
    "new_historic_deaths": "0"
  },
  {
    "date_updated": "2022-08-04T00:00:00.000",
    "state": "SC",
    "start_date": "2022-07-28T00:00:00.000",
    "end_date": "2022-08-03T00:00:00.000",
    "tot_cases": "1621121.0",
    "new_cases": "15956.0",
    "tot_deaths": "18208.0",
    "new_deaths": "19.0",
    "new_historic_cases": "0",
    "new_historic_deaths": "0"
  },
  {
    "date_updated": "2022-08-11T00:00:00.000",
    "state": "SC",
    "start_date": "2022-08-04T00:00:00.000",
    "end_date": "2022-08-10T00:00:00.000",
    "tot_cases": "1637108.0",
    "new_cases": "15987.0",
    "tot_deaths": "18215.0",
    "new_deaths": "7.0",
    "new_historic_cases": "0",
    "new_historic_deaths": "0"
  },
  {
    "date_updated": "2022-08-18T00:00:00.000",
    "state": "SC",
    "start_date": "2022-08-11T00:00:00.000",
    "end_date": "2022-08-17T00:00:00.000",
    "tot_cases": "1650748.0",
    "new_cases": "13640.0",
    "tot_deaths": "18227.0",
    "new_deaths": "12.0",
    "new_historic_cases": "0",
    "new_historic_deaths": "0"
  },
  {
    "date_updated": "2022-08-25T00:00:00.000",
    "state": "SC",
    "start_date": "2022-08-18T00:00:00.000",
    "end_date": "2022-08-24T00:00:00.000",
    "tot_cases": "1661020.0",
    "new_cases": "10272.0",
    "tot_deaths": "18245.0",
    "new_deaths": "18.0",
    "new_historic_cases": "0",
    "new_historic_deaths": "0"
  },
  {
    "date_updated": "2022-09-01T00:00:00.000",
    "state": "SC",
    "start_date": "2022-08-25T00:00:00.000",
    "end_date": "2022-08-31T00:00:00.000",
    "tot_cases": "1674281.0",
    "new_cases": "13261.0",
    "tot_deaths": "18263.0",
    "new_deaths": "18.0",
    "new_historic_cases": "0",
    "new_historic_deaths": "0"
  },
  {
    "date_updated": "2022-09-08T00:00:00.000",
    "state": "SC",
    "start_date": "2022-09-01T00:00:00.000",
    "end_date": "2022-09-07T00:00:00.000",
    "tot_cases": "1687640.0",
    "new_cases": "13359.0",
    "tot_deaths": "18299.0",
    "new_deaths": "36.0",
    "new_historic_cases": "0",
    "new_historic_deaths": "0"
  },
  {
    "date_updated": "2022-09-15T00:00:00.000",
    "state": "SC",
    "start_date": "2022-09-08T00:00:00.000",
    "end_date": "2022-09-14T00:00:00.000",
    "tot_cases": "1696746.0",
    "new_cases": "9106.0",
    "tot_deaths": "18316.0",
    "new_deaths": "17.0",
    "new_historic_cases": "0",
    "new_historic_deaths": "0"
  },
  {
    "date_updated": "2022-09-22T00:00:00.000",
    "state": "SC",
    "start_date": "2022-09-15T00:00:00.000",
    "end_date": "2022-09-21T00:00:00.000",
    "tot_cases": "1703439.0",
    "new_cases": "6693.0",
    "tot_deaths": "18331.0",
    "new_deaths": "15.0",
    "new_historic_cases": "0",
    "new_historic_deaths": "0"
  },
  {
    "date_updated": "2022-09-29T00:00:00.000",
    "state": "SC",
    "start_date": "2022-09-22T00:00:00.000",
    "end_date": "2022-09-28T00:00:00.000",
    "tot_cases": "1708074.0",
    "new_cases": "4635.0",
    "tot_deaths": "18365.0",
    "new_deaths": "34.0",
    "new_historic_cases": "0",
    "new_historic_deaths": "0"
  },
  {
    "date_updated": "2022-10-06T00:00:00.000",
    "state": "SC",
    "start_date": "2022-09-29T00:00:00.000",
    "end_date": "2022-10-05T00:00:00.000",
    "tot_cases": "1712281.0",
    "new_cases": "4207.0",
    "tot_deaths": "18390.0",
    "new_deaths": "25.0",
    "new_historic_cases": "0",
    "new_historic_deaths": "0"
  },
  {
    "date_updated": "2022-10-13T00:00:00.000",
    "state": "SC",
    "start_date": "2022-10-06T00:00:00.000",
    "end_date": "2022-10-12T00:00:00.000",
    "tot_cases": "1715434.0",
    "new_cases": "3153.0",
    "tot_deaths": "18468.0",
    "new_deaths": "78.0",
    "new_historic_cases": "0",
    "new_historic_deaths": "0"
  },
  {
    "date_updated": "2022-10-20T00:00:00.000",
    "state": "SC",
    "start_date": "2022-10-13T00:00:00.000",
    "end_date": "2022-10-19T00:00:00.000",
    "tot_cases": "1718600.0",
    "new_cases": "3166.0",
    "tot_deaths": "18527.0",
    "new_deaths": "59.0",
    "new_historic_cases": "0",
    "new_historic_deaths": "0"
  },
  {
    "date_updated": "2022-10-27T00:00:00.000",
    "state": "SC",
    "start_date": "2022-10-20T00:00:00.000",
    "end_date": "2022-10-26T00:00:00.000",
    "tot_cases": "1721693.0",
    "new_cases": "3093.0",
    "tot_deaths": "18578.0",
    "new_deaths": "51.0",
    "new_historic_cases": "0",
    "new_historic_deaths": "0"
  },
  {
    "date_updated": "2022-11-03T00:00:00.000",
    "state": "SC",
    "start_date": "2022-10-27T00:00:00.000",
    "end_date": "2022-11-02T00:00:00.000",
    "tot_cases": "1725160.0",
    "new_cases": "3467.0",
    "tot_deaths": "18633.0",
    "new_deaths": "55.0",
    "new_historic_cases": "0",
    "new_historic_deaths": "0"
  },
  {
    "date_updated": "2022-11-10T00:00:00.000",
    "state": "SC",
    "start_date": "2022-11-03T00:00:00.000",
    "end_date": "2022-11-09T00:00:00.000",
    "tot_cases": "1729333.0",
    "new_cases": "4173.0",
    "tot_deaths": "18660.0",
    "new_deaths": "27.0",
    "new_historic_cases": "0",
    "new_historic_deaths": "0"
  },
  {
    "date_updated": "2022-11-17T00:00:00.000",
    "state": "SC",
    "start_date": "2022-11-10T00:00:00.000",
    "end_date": "2022-11-16T00:00:00.000",
    "tot_cases": "1732287.0",
    "new_cases": "2954.0",
    "tot_deaths": "18678.0",
    "new_deaths": "18.0",
    "new_historic_cases": "0",
    "new_historic_deaths": "0"
  },
  {
    "date_updated": "2022-11-24T00:00:00.000",
    "state": "SC",
    "start_date": "2022-11-17T00:00:00.000",
    "end_date": "2022-11-23T00:00:00.000",
    "tot_cases": "1735351.0",
    "new_cases": "3064.0",
    "tot_deaths": "18706.0",
    "new_deaths": "28.0",
    "new_historic_cases": "0",
    "new_historic_deaths": "0"
  },
  {
    "date_updated": "2022-12-01T00:00:00.000",
    "state": "SC",
    "start_date": "2022-11-24T00:00:00.000",
    "end_date": "2022-11-30T00:00:00.000",
    "tot_cases": "1738379.0",
    "new_cases": "3028.0",
    "tot_deaths": "18710.0",
    "new_deaths": "4.0",
    "new_historic_cases": "0",
    "new_historic_deaths": "0"
  },
  {
    "date_updated": "2022-12-08T00:00:00.000",
    "state": "SC",
    "start_date": "2022-12-01T00:00:00.000",
    "end_date": "2022-12-07T00:00:00.000",
    "tot_cases": "1745168.0",
    "new_cases": "6789.0",
    "tot_deaths": "18756.0",
    "new_deaths": "46.0",
    "new_historic_cases": "0",
    "new_historic_deaths": "0"
  },
  {
    "date_updated": "2022-12-15T00:00:00.000",
    "state": "SC",
    "start_date": "2022-12-08T00:00:00.000",
    "end_date": "2022-12-14T00:00:00.000",
    "tot_cases": "1751646.0",
    "new_cases": "6478.0",
    "tot_deaths": "18783.0",
    "new_deaths": "27.0",
    "new_historic_cases": "0",
    "new_historic_deaths": "0"
  },
  {
    "date_updated": "2022-12-22T00:00:00.000",
    "state": "SC",
    "start_date": "2022-12-15T00:00:00.000",
    "end_date": "2022-12-21T00:00:00.000",
    "tot_cases": "1760204.0",
    "new_cases": "8558.0",
    "tot_deaths": "18811.0",
    "new_deaths": "28.0",
    "new_historic_cases": "0",
    "new_historic_deaths": "0"
  },
  {
    "date_updated": "2022-12-29T00:00:00.000",
    "state": "SC",
    "start_date": "2022-12-22T00:00:00.000",
    "end_date": "2022-12-28T00:00:00.000",
    "tot_cases": "1770059.0",
    "new_cases": "9855.0",
    "tot_deaths": "18834.0",
    "new_deaths": "23.0",
    "new_historic_cases": "0",
    "new_historic_deaths": "0"
  },
  {
    "date_updated": "2023-01-05T00:00:00.000",
    "state": "SC",
    "start_date": "2022-12-29T00:00:00.000",
    "end_date": "2023-01-04T00:00:00.000",
    "tot_cases": "1780649.0",
    "new_cases": "10590.0",
    "tot_deaths": "18849.0",
    "new_deaths": "15.0",
    "new_historic_cases": "0",
    "new_historic_deaths": "0"
  },
  {
    "date_updated": "2023-01-12T00:00:00.000",
    "state": "SC",
    "start_date": "2023-01-05T00:00:00.000",
    "end_date": "2023-01-11T00:00:00.000",
    "tot_cases": "1791933.0",
    "new_cases": "11284.0",
    "tot_deaths": "18983.0",
    "new_deaths": "134.0",
    "new_historic_cases": "0",
    "new_historic_deaths": "0"
  },
  {
    "date_updated": "2023-01-19T00:00:00.000",
    "state": "SC",
    "start_date": "2023-01-12T00:00:00.000",
    "end_date": "2023-01-18T00:00:00.000",
    "tot_cases": "1799966.0",
    "new_cases": "8033.0",
    "tot_deaths": "19069.0",
    "new_deaths": "86.0",
    "new_historic_cases": "0",
    "new_historic_deaths": "0"
  },
  {
    "date_updated": "2023-01-26T00:00:00.000",
    "state": "SC",
    "start_date": "2023-01-19T00:00:00.000",
    "end_date": "2023-01-25T00:00:00.000",
    "tot_cases": "1807019.0",
    "new_cases": "7053.0",
    "tot_deaths": "19093.0",
    "new_deaths": "24.0",
    "new_historic_cases": "0",
    "new_historic_deaths": "0"
  },
  {
    "date_updated": "2023-02-02T00:00:00.000",
    "state": "SC",
    "start_date": "2023-01-26T00:00:00.000",
    "end_date": "2023-02-01T00:00:00.000",
    "tot_cases": "1812958.0",
    "new_cases": "5939.0",
    "tot_deaths": "19226.0",
    "new_deaths": "133.0",
    "new_historic_cases": "0",
    "new_historic_deaths": "0"
  },
  {
    "date_updated": "2023-02-09T00:00:00.000",
    "state": "SC",
    "start_date": "2023-02-02T00:00:00.000",
    "end_date": "2023-02-08T00:00:00.000",
    "tot_cases": "1818546.0",
    "new_cases": "5588.0",
    "tot_deaths": "19330.0",
    "new_deaths": "104.0",
    "new_historic_cases": "0",
    "new_historic_deaths": "0"
  },
  {
    "date_updated": "2023-02-16T00:00:00.000",
    "state": "SC",
    "start_date": "2023-02-09T00:00:00.000",
    "end_date": "2023-02-15T00:00:00.000",
    "tot_cases": "1823413.0",
    "new_cases": "4867.0",
    "tot_deaths": "19393.0",
    "new_deaths": "63.0",
    "new_historic_cases": "0",
    "new_historic_deaths": "0"
  },
  {
    "date_updated": "2023-02-23T00:00:00.000",
    "state": "SC",
    "start_date": "2023-02-16T00:00:00.000",
    "end_date": "2023-02-22T00:00:00.000",
    "tot_cases": "1827620.0",
    "new_cases": "4207.0",
    "tot_deaths": "19489.0",
    "new_deaths": "96.0",
    "new_historic_cases": "0",
    "new_historic_deaths": "0"
  },
  {
    "date_updated": "2023-03-02T00:00:00.000",
    "state": "SC",
    "start_date": "2023-02-23T00:00:00.000",
    "end_date": "2023-03-01T00:00:00.000",
    "tot_cases": "1833731.0",
    "new_cases": "6111.0",
    "tot_deaths": "19531.0",
    "new_deaths": "42.0",
    "new_historic_cases": "0",
    "new_historic_deaths": "0"
  },
  {
    "date_updated": "2023-03-09T00:00:00.000",
    "state": "SC",
    "start_date": "2023-03-02T00:00:00.000",
    "end_date": "2023-03-08T00:00:00.000",
    "tot_cases": "1836568.0",
    "new_cases": "2837.0",
    "tot_deaths": "19599.0",
    "new_deaths": "68.0",
    "new_historic_cases": "0",
    "new_historic_deaths": "0"
  },
  {
    "date_updated": "2023-03-16T00:00:00.000",
    "state": "SC",
    "start_date": "2023-03-09T00:00:00.000",
    "end_date": "2023-03-15T00:00:00.000",
    "tot_cases": "1838465.0",
    "new_cases": "1897.0",
    "tot_deaths": "19653.0",
    "new_deaths": "54.0",
    "new_historic_cases": "0",
    "new_historic_deaths": "0"
  },
  {
    "date_updated": "2023-03-23T00:00:00.000",
    "state": "SC",
    "start_date": "2023-03-16T00:00:00.000",
    "end_date": "2023-03-22T00:00:00.000",
    "tot_cases": "1840458.0",
    "new_cases": "1993.0",
    "tot_deaths": "19672.0",
    "new_deaths": "19.0",
    "new_historic_cases": "0",
    "new_historic_deaths": "0"
  },
  {
    "date_updated": "2023-03-30T00:00:00.000",
    "state": "SC",
    "start_date": "2023-03-23T00:00:00.000",
    "end_date": "2023-03-29T00:00:00.000",
    "tot_cases": "1842519.0",
    "new_cases": "2061.0",
    "tot_deaths": "19683.0",
    "new_deaths": "11.0",
    "new_historic_cases": "0",
    "new_historic_deaths": "0"
  },
  {
    "date_updated": "2023-04-06T00:00:00.000",
    "state": "SC",
    "start_date": "2023-03-30T00:00:00.000",
    "end_date": "2023-04-05T00:00:00.000",
    "tot_cases": "1844314.0",
    "new_cases": "1795.0",
    "tot_deaths": "19744.0",
    "new_deaths": "61.0",
    "new_historic_cases": "0",
    "new_historic_deaths": "0"
  },
  {
    "date_updated": "2023-04-13T00:00:00.000",
    "state": "SC",
    "start_date": "2023-04-06T00:00:00.000",
    "end_date": "2023-04-12T00:00:00.000",
    "tot_cases": "1846130.0",
    "new_cases": "1816.0",
    "tot_deaths": "19786.0",
    "new_deaths": "42.0",
    "new_historic_cases": "0",
    "new_historic_deaths": "0"
  },
  {
    "date_updated": "2023-04-20T00:00:00.000",
    "state": "SC",
    "start_date": "2023-04-13T00:00:00.000",
    "end_date": "2023-04-19T00:00:00.000",
    "tot_cases": "1848020.0",
    "new_cases": "1890.0",
    "tot_deaths": "19836.0",
    "new_deaths": "50.0",
    "new_historic_cases": "0",
    "new_historic_deaths": "0"
  },
  {
    "date_updated": "2023-04-27T00:00:00.000",
    "state": "SC",
    "start_date": "2023-04-20T00:00:00.000",
    "end_date": "2023-04-26T00:00:00.000",
    "tot_cases": "1849390.0",
    "new_cases": "1370.0",
    "tot_deaths": "19851.0",
    "new_deaths": "15.0",
    "new_historic_cases": "0",
    "new_historic_deaths": "0"
  },
  {
    "date_updated": "2023-05-04T00:00:00.000",
    "state": "SC",
    "start_date": "2023-04-27T00:00:00.000",
    "end_date": "2023-05-03T00:00:00.000",
    "tot_cases": "1850662.0",
    "new_cases": "1272.0",
    "tot_deaths": "19901.0",
    "new_deaths": "50.0",
    "new_historic_cases": "0",
    "new_historic_deaths": "0"
  },
  {
    "date_updated": "2023-05-11T00:00:00.000",
    "state": "SC",
    "start_date": "2023-05-04T00:00:00.000",
    "end_date": "2023-05-10T00:00:00.000",
    "tot_cases": "1852019.0",
    "new_cases": "1357.0",
    "tot_deaths": "19923.0",
    "new_deaths": "22.0",
    "new_historic_cases": "0",
    "new_historic_deaths": "0"
  }
]